[{"Country": "Argentina", "Sales": 75232.530654948}, {"Country": "Canada", "Sales": 417371.1928899906}, {"Country": "France", "Sales": 1393897.4990173313}, {"Country": "Germany", "Sales": 4216296.0179977575}, {"Country": "Italy", "Sales": 104869.0187075601}, {"Country": "Norway", "Sales": 1706.1020538}, {"Country": "Poland", "Sales": 34625.88008252}, {"Country": "Singapore", "Sales": 4485638.041253188}, {"Country": "Spain", "Sales": 219006.633798626}, {"Country": "Sweden", "Sales": 447345.3790355402}, {"Country": "Switzerland", "Sales": 103991.089346264}, {"Country": "UK", "Sales": 1270790.101232497}, {"Country": "USA", "Sales": 1478576.31726807}]